jupyter_education/__init__.py
jupyter_education/_version.py
jupyter_education/handlers.py
jupyter_education/tests/__init__.py
jupyter_education/tests/test_handlers.py
jupyter_education-0.0.3.data/data/etc/jupyter/jupyter_notebook_config.d/jupyter_education.json
jupyter_education-0.0.3.data/data/etc/jupyter/jupyter_server_config.d/jupyter_education.json
jupyter_education-0.0.3.data/data/share/jupyter/labextensions/@datalayer/jupyter-education/build_log.json
jupyter_education-0.0.3.data/data/share/jupyter/labextensions/@datalayer/jupyter-education/package.json
jupyter_education-0.0.3.data/data/share/jupyter/labextensions/@datalayer/jupyter-education/schemas/@datalayer/jupyter-education/package.json.orig
jupyter_education-0.0.3.data/data/share/jupyter/labextensions/@datalayer/jupyter-education/schemas/@datalayer/jupyter-education/plugin.json
jupyter_education-0.0.3.data/data/share/jupyter/labextensions/@datalayer/jupyter-education/static/lib_index_js.1a4a1a3c87f78e987ee7.js
jupyter_education-0.0.3.data/data/share/jupyter/labextensions/@datalayer/jupyter-education/static/lib_index_js.1a4a1a3c87f78e987ee7.js.map
jupyter_education-0.0.3.data/data/share/jupyter/labextensions/@datalayer/jupyter-education/static/remoteEntry.9be03b7293c8d9b2caf2.js
jupyter_education-0.0.3.data/data/share/jupyter/labextensions/@datalayer/jupyter-education/static/remoteEntry.9be03b7293c8d9b2caf2.js.map
jupyter_education-0.0.3.data/data/share/jupyter/labextensions/@datalayer/jupyter-education/static/style.js
jupyter_education-0.0.3.data/data/share/jupyter/labextensions/@datalayer/jupyter-education/static/style_index_js.46492fe61a8f9465dcf6.js
jupyter_education-0.0.3.data/data/share/jupyter/labextensions/@datalayer/jupyter-education/static/style_index_js.46492fe61a8f9465dcf6.js.map
jupyter_education-0.0.3.dist-info/METADATA
jupyter_education-0.0.3.dist-info/WHEEL
jupyter_education-0.0.3.dist-info/licenses/LICENSE
jupyter_education-0.0.3.dist-info/RECORD
